pystrapi/__init__.py
pystrapi/_utils.py
pystrapi/connector.py
pystrapi/connector_sync.py
pystrapi/errors.py
pystrapi/help/__init__.py
pystrapi/help/aiohttp_helpers.py
pystrapi/help/helpers.py
pystrapi/help/requests_helpers.py
pystrapi/parameters.py
pystrapi/strapi_client.py
pystrapi/strapi_client_sync.py
pystrapi/types.py
pystrapi-4.5.0.dist-info/LICENSE
pystrapi-4.5.0.dist-info/WHEEL
pystrapi-4.5.0.dist-info/METADATA
pystrapi-4.5.0.dist-info/RECORD
