Metadata-Version: 2.1
Name: pystrapi
Version: 4.5.0
Summary: Work with Strapi from Python via REST API
Home-page: https://github.com/NoamNol/py-strapi
License: MIT
Keywords: strapi,cms,api,rest
Author: Noam Nol
Author-email: noamnol19@gmail.com
Requires-Python: >=3.8,<4.0
Classifier: License :: OSI Approved :: MIT License
Classifier: Operating System :: OS Independent
Classifier: Programming Language :: Python :: 3
Classifier: Programming Language :: Python :: 3.10
Classifier: Programming Language :: Python :: 3.8
Classifier: Programming Language :: Python :: 3.9
Requires-Dist: aiohttp
Requires-Dist: requests (>=2.25.0,<3.0.0)
Project-URL: Repository, https://github.com/NoamNol/py-strapi
